megabank_package/account.py
megabank_package/current_account.py
megabank_package/saving_account.py
megabank_package-1.0.dist-info/METADATA
megabank_package-1.0.dist-info/WHEEL
megabank_package-1.0.dist-info/top_level.txt
megabank_package-1.0.dist-info/RECORD
