Metadata-Version: 2.1
Name: megabank-package
Version: 1.0
Summary: API package that provides us the method to fetch the data from the API, along with the method to convert that into proper dataframe
Author: Nivedita
Author-email: niveditashinde70@gmail.com
License: MIT
Requires-Dist: pandas
Requires-Dist: requests
